Workbook

Sheet Calculo
A1: Ejecución del presupuesto y del tiempo · corte Sprint 9
A3: Línea base (SCRUM-11, SCRUM-24, SCRUM-36, SCRUM-57)
A4: Esfuerzo total estimado (H/H) | B4: 7613.67 | C4: SCRUM-11, Puntos de Casos de Uso
A5: Costo total estimado, K = 1.5 | B5: 511638.46 | C5: SCRUM-11
A6: Costo total estimado, K = 2 | B6: 682184.62 | C6: SCRUM-11
A7: Factor K bajo | B7: 1.5 | C7: Multiplica la tarifa horaria
A8: Factor K alto | B8: 2 | C8: Multiplica la tarifa horaria
A9: Peso de la actividad de implementación | B9: 0.4 | C9: Métrica dual, SCRUM-24 y SCRUM-36
A10: Horas acumuladas al cierre del Sprint 8 (H/H) | B10: 811 | C10: 721.00 del S7 + horas del S8 (ejecucion-presupuesto-sprint8.xlsx)
A11: Monto ejecutado al cierre del Sprint 8, K = 1.5 | B11: 54785.7 | C11: Q 48,701.70 del S7 + monto del S8 con K = 1.5
A13: Horas y monto del Sprint 9 por integrante
A14: Integrante | B14: Tarifa (Q/h) | C14: Horas del S9 (H/H) | D14: % de las horas del S9 | E14: Monto base (Q) | F14: Monto K = 1.5 (Q) | G14: Monto K = 2 (Q)
A15: Pablo Vásquez | B15: 57 | C15: =SUMIF('Tareas S9'!$C$4:$C$15,A15,'Tareas S9'!$F$4:$F$15) -> 19 | D15: =IF($C$20=0,0,C15/$C$20) -> 0.21590909 | E15: =C15*B15 -> 1083 | F15: =E15*$B$7 -> 1624.5 | G15: =E15*$B$8 -> 2166
A16: Jonathan Tubac | B16: 51 | C16: =SUMIF('Tareas S9'!$C$4:$C$15,A16,'Tareas S9'!$F$4:$F$15) -> 18 | D16: =IF($C$20=0,0,C16/$C$20) -> 0.20454545 | E16: =C16*B16 -> 918 | F16: =E16*$B$7 -> 1377 | G16: =E16*$B$8 -> 1836
A17: Juan Francisco Montenegro Aguirre | B17: 46 | C17: =SUMIF('Tareas S9'!$C$4:$C$15,A17,'Tareas S9'!$F$4:$F$15) -> 23 | D17: =IF($C$20=0,0,C17/$C$20) -> 0.26136364 | E17: =C17*B17 -> 1058 | F17: =E17*$B$7 -> 1587 | G17: =E17*$B$8 -> 2116
A18: Alejandra Sarai Avilés González | B18: 36 | C18: =SUMIF('Tareas S9'!$C$4:$C$15,A18,'Tareas S9'!$F$4:$F$15) -> 13 | D18: =IF($C$20=0,0,C18/$C$20) -> 0.14772727 | E18: =C18*B18 -> 468 | F18: =E18*$B$7 -> 702 | G18: =E18*$B$8 -> 936
A19: Ivana Cristina Figueroa Diemek | B19: 34 | C19: =SUMIF('Tareas S9'!$C$4:$C$15,A19,'Tareas S9'!$F$4:$F$15) -> 15 | D19: =IF($C$20=0,0,C19/$C$20) -> 0.17045455 | E19: =C19*B19 -> 510 | F19: =E19*$B$7 -> 765 | G19: =E19*$B$8 -> 1020
A20: Total | B20: =IF(C20=0,0,E20/C20) -> 45.875 | C20: =SUM(C15:C19) -> 88 | D20: =SUM(D15:D19) -> 1 | E20: =SUM(E15:E19) -> 4037 | F20: =SUM(F15:F19) -> 6055.5 | G20: =SUM(G15:G19) -> 8074
A23: Resultados y variación respecto del corte del Sprint 8
A24: Indicador | B24: Corte Sprint 8 | C24: Corte Sprint 9 | D24: Variación
A25: Horas acumuladas (H/H) | B25: =B10 -> 811 | C25: =B10+C20 -> 899 | D25: =C25-B25 -> 88
A26: % del esfuerzo total (ciclo completo) | B26: =B25/$B$4 -> 0.10651893 | C26: =C25/$B$4 -> 0.11807709 | D26: =(C26-B26)*100 -> 1.1558158
A27: % de la actividad de implementación (40 %) | B27: =B25/($B$4*$B$9) -> 0.26629733 | C27: =C25/($B$4*$B$9) -> 0.29519273 | D27: =(C27-B27)*100 -> 2.8895395
A28: Monto ejecutado, K = 1.5 | B28: =B11 -> 54785.7 | C28: =B11+F20 -> 60841.2 | D28: =C28-B28 -> 6055.5
A29: % del costo total, K = 1.5 | B29: =B28/$B$5 -> 0.10707893 | C29: =C28/$B$5 -> 0.11891444 | D29: =(C29-B29)*100 -> 1.1835506
A30: Monto ejecutado, K = 2 | B30: =B11/$B$7*$B$8 -> 73047.6 | C30: =B30+G20 -> 81121.6 | D30: =C30-B30 -> 8074
A31: % del costo total, K = 2 | B31: =B30/$B$6 -> 0.10707893 | C31: =C30/$B$6 -> 0.11891444 | D31: =(C31-B31)*100 -> 1.1835506
A32: % del costo de implementación, K = 1.5 | B32: =B28/($B$5*$B$9) -> 0.26769733 | C32: =C28/($B$5*$B$9) -> 0.2972861 | D32: =(C32-B32)*100 -> 2.9588765
A33: Horas restantes del esfuerzo total (H/H) | B33: =$B$4-B25 -> 6802.67 | C33: =$B$4-C25 -> 6714.67 | D33: =C33-B33 -> -88
A34: Saldo del presupuesto, K = 1.5 | B34: =$B$5-B28 -> 456852.76 | C34: =$B$5-C28 -> 450797.26 | D34: =C34-B34 -> -6055.5
A35: Variación de los porcentajes en puntos porcentuales.

Sheet Tareas S9
A1: Tareas del Sprint 9 en Jira (SCRUM Sprint 4) y horas registradas
A3: Clave | B3: Tarea | C3: Responsable | D3: SP | E3: Horas estimadas en Jira | F3: Horas en LOGT | G3: Diferencia | H3: Estado en Jira
A4: SCRUM-63 | B4: UX-R3 · Contraste del texto secundario según WCAG AA | C4: Pablo Vásquez | D4: 3 | E4: 6 | F4: =SUMIF('LOGT Vásquez'!$G:$G,A4,'LOGT Vásquez'!$E:$E)/60 -> 6 | G4: =F4-E4 -> 0 | H4: Finalizado
A5: SCRUM-70 | B5: G-1 · Regresión de pruebas de seguridad y volumen | C5: Pablo Vásquez | D5: 3 | E5: 8 | F5: =SUMIF('LOGT Vásquez'!$G:$G,A5,'LOGT Vásquez'!$E:$E)/60 -> 8 | G5: =F5-E5 -> 0 | H5: Finalizado
A6: SCRUM-74 | B6: G-7 · Automatización en CI de pruebas unitarias y de carga | C6: Pablo Vásquez | D6: 2 | E6: 5 | F6: =SUMIF('LOGT Vásquez'!$G:$G,A6,'LOGT Vásquez'!$E:$E)/60 -> 5 | G6: =F6-E6 -> 0 | H6: Finalizado
A7: SCRUM-65 | B7: UX-R5 · Controles reconocibles en Integraciones | C7: Jonathan Tubac | D7: 3 | E7: 5 | F7: =SUMIF('LOGT Tubac'!$G:$G,A7,'LOGT Tubac'!$E:$E)/60 -> 5 | G7: =F7-E7 -> 0 | H7: Finalizado
A8: SCRUM-67 | B8: DT-15 · Timeouts salientes, pool y verificación TLS | C8: Jonathan Tubac | D8: 3 | E8: 5 | F8: =SUMIF('LOGT Tubac'!$G:$G,A8,'LOGT Tubac'!$E:$E)/60 -> 5 | G8: =F8-E8 -> 0 | H8: Finalizado
A9: SCRUM-72 | B9: G-5 · Presupuesto y tiempo ejecutado al cierre del Sprint 9 | C9: Jonathan Tubac | D9: 3 | E9: 8 | F9: =SUMIF('LOGT Tubac'!$G:$G,A9,'LOGT Tubac'!$E:$E)/60 -> 8 | G9: =F9-E9 -> 0 | H9: Finalizado
A10: SCRUM-61 | B10: UX-R1 · Internacionalización y persistencia del idioma | C10: Juan Francisco Montenegro Aguirre | D10: 5 | E10: 10 | F10: =SUMIF('LOGT Montenegro'!$G:$G,A10,'LOGT Montenegro'!$E:$E)/60 -> 10 | G10: =F10-E10 -> 0 | H10: Finalizado
A11: SCRUM-71 | B11: G-2 · Comparativa de pruebas no funcionales vs RNF y plan de refactorización | C11: Juan Francisco Montenegro Aguirre | D11: 5 | E11: 13 | F11: =SUMIF('LOGT Montenegro'!$G:$G,A11,'LOGT Montenegro'!$E:$E)/60 -> 13 | G11: =F11-E11 -> 0 | H11: Finalizado
A12: SCRUM-64 | B12: UX-R4 · Rediseño de la portada de la landing | C12: Alejandra Sarai Avilés González | D12: 5 | E12: 8 | F12: =SUMIF('LOGT Avilés'!$G:$G,A12,'LOGT Avilés'!$E:$E)/60 -> 8 | G12: =F12-E12 -> 0 | H12: Finalizado
A13: SCRUM-73 | B13: G-6 · Demo del incremento a usuarios finales | C13: Alejandra Sarai Avilés González | D13: 2 | E13: 5 | F13: =SUMIF('LOGT Avilés'!$G:$G,A13,'LOGT Avilés'!$E:$E)/60 -> 5 | G13: =F13-E13 -> 0 | H13: Finalizado
A14: SCRUM-62 | B14: UX-R2 · Navegación: Ventas y Configuración unificada | C14: Ivana Cristina Figueroa Diemek | D14: 5 | E14: 10 | F14: =SUMIF('LOGT Figueroa'!$G:$G,A14,'LOGT Figueroa'!$E:$E)/60 -> 10 | G14: =F14-E14 -> 0 | H14: Finalizado
A15: SCRUM-68 | B15: DT-10 · Endpoint agregado de presupuesto (elimina N+1) | C15: Ivana Cristina Figueroa Diemek | D15: 3 | E15: 5 | F15: =SUMIF('LOGT Figueroa'!$G:$G,A15,'LOGT Figueroa'!$E:$E)/60 -> 5 | G15: =F15-E15 -> 0 | H15: Finalizado
A16: Total | D16: =SUM(D4:D15) -> 42 | E16: =SUM(E4:E15) -> 88 | F16: =SUM(F4:F15) -> 88 | G16: =SUM(G4:G15) -> 0
A18: Las horas usadas salen de los LOGT; cuadran con la estimación de Jira de cada tarea, igual que en el corte del Sprint 8.

Sheet Serie
A1: Serie de cortes: horas y monto acumulados
A3: Corte | B3: Horas del periodo (H/H) | C3: Horas acumuladas (H/H) | D3: % del esfuerzo total | E3: Monto acumulado K = 1.5 | F3: % del costo K = 1.5 | G3: Fuente
A4: Sprints 1 a 4 | B4: 514.5 | C4: 514.5 | D4: =C4/Calculo!$B$4 -> 0.067575821 | E4: No reportado por separado | G4: LOGT, reportado en SCRUM-24
A5: Sprints 5 a 7 | B5: 206.5 | C5: 721 | D5: =C5/Calculo!$B$4 -> 0.094698089 | E5: 48701.7 | F5: =E5/Calculo!$B$5 -> 0.095187723 | G5: SCRUM-36
A6: Sprint 8 | B6: =Calculo!B10-C5 -> 90 | C6: =Calculo!B10 -> 811 | D6: =C6/Calculo!$B$4 -> 0.10651893 | E6: =Calculo!B11 -> 54785.7 | F6: =E6/Calculo!$B$5 -> 0.10707893 | G6: SCRUM-57, ejecucion-presupuesto-sprint8.xlsx
A7: Sprint 9 | B7: =Calculo!C20 -> 88 | C7: =Calculo!C25 -> 899 | D7: =C7/Calculo!$B$4 -> 0.11807709 | E7: =Calculo!C28 -> 60841.2 | F7: =E7/Calculo!$B$5 -> 0.11891444 | G7: SCRUM-72, este libro
A9: El corte del Sprint 6 no se reportó por separado: SCRUM-36 consolidó los Sprints 6 y 7 en un solo corte.

Sheet Texto
A1: Texto para el informe
A3: ="En el Sprint 9 se registran "&TEXT(Calculo!C20,"#,##0")&" H/H según los LOGT de los cinco integrantes. Con ello el equipo acumula "&TEXT(Calculo!C25,"#,##0.00")&" H/H, equivalentes al "&TEXT(Calculo!C26,"0.00%")&" del esfuerzo total estimado de "&TEXT(Calculo!B4,"#,##0.00")&" H/H, un avance de "&TEXT(Calculo!D26,"0.00")&" puntos porcentuales respecto del corte del Sprint 8 ("&TEXT(Calculo!B26,"0.00%")&")." -> En el Sprint 9 se registran 88 H/H según los LOGT de los cinco integrantes. Con ello el equipo acumula 899.00 H/H, equivalentes al 11.81% del esfuerzo total estimado de 7,613.67 H/H, un avance de 1.16 puntos porcentuales respecto del corte del Sprint 8 (10.65%).
A5: ="Con la tarifa individual de cada integrante, el Sprint 9 suma Q "&TEXT(Calculo!F20,"#,##0.00")&" con K = 1.5, y el monto ejecutado acumulado asciende a Q "&TEXT(Calculo!C28,"#,##0.00")&", el "&TEXT(Calculo!C29,"0.00%")&" del costo total estimado (Q "&TEXT(Calculo!B5,"#,##0.00")&"). Con K = 2 son Q "&TEXT(Calculo!C30,"#,##0.00")&" sobre Q "&TEXT(Calculo!B6,"#,##0.00")&", la misma proporción. Frente al Sprint 8, el porcentaje de costo avanza "&TEXT(Calculo!D29,"0.00")&" puntos porcentuales." -> Con la tarifa individual de cada integrante, el Sprint 9 suma Q 6,055.50 con K = 1.5, y el monto ejecutado acumulado asciende a Q 60,841.20, el 11.89% del costo total estimado (Q 511,638.46). Con K = 2 son Q 81,121.60 sobre Q 682,184.62, la misma proporción. Frente al Sprint 8, el porcentaje de costo avanza 1.18 puntos porcentuales.
A7: ="Métrica dual: frente al esfuerzo de ciclo completo del PCU se ha consumido el "&TEXT(Calculo!C26,"0.00%")&"; frente a la actividad de implementación (40 % del esfuerzo, "&TEXT(Calculo!B4*Calculo!B9,"#,##0.00")&" H/H) el consumo es del "&TEXT(Calculo!C27,"0.00%")&", y en costo del "&TEXT(Calculo!C32,"0.00%")&"." -> Métrica dual: frente al esfuerzo de ciclo completo del PCU se ha consumido el 11.81%; frente a la actividad de implementación (40 % del esfuerzo, 3,045.47 H/H) el consumo es del 29.52%, y en costo del 29.73%.
A9: Interpretación: el gasto no va adelantado respecto del avance funcional, va muy por detrás. El backlog funcional está prácticamente completo y los últimos sprints se dedican a pruebas no funcionales, deuda técnica y mejoras de usabilidad, mientras el porcentaje consumido sigue cerca del 12 %. La desviación no es un error de cálculo: el método de Karner está calibrado para el ciclo de vida profesional completo (análisis, diseño, implementación, pruebas, despliegue y gestión) y opera como cota superior. El porcentaje frente a la actividad de implementación es la lectura más cercana al trabajo realizado.
A11: ="Proyección: al ritmo de los últimos dos sprints (unas "&TEXT((Serie!B6+Serie!B7)/2,"0")&" H/H por sprint), el saldo de "&TEXT(Calculo!C33,"#,##0")&" H/H y Q "&TEXT(Calculo!C34,"#,##0.00")&" (K = 1.5) alcanza con holgura para los sprints restantes. El presupuesto no es la restricción del proyecto; lo es el calendario académico." -> Proyección: al ritmo de los últimos dos sprints (unas 89 H/H por sprint), el saldo de 6,715 H/H y Q 450,797.26 (K = 1.5) alcanza con holgura para los sprints restantes. El presupuesto no es la restricción del proyecto; lo es el calendario académico.

Sheet LOGT Vásquez
A1: Registro de tiempo (LOGT) · Sprint 9
A3: Integrante | B3: Pablo Vásquez
A4: Carné | B4: 24757
A5: Sprint | B5: Sprint 9 (Jira: SCRUM Sprint 4), 08/10/2026 – 13/10/2026
A6: Proyecto | B6: Kontrol
A8: Fecha | B8: Inicio | C8: Fin | D8: Interrupción (min) | E8: Δ Tiempo (min) | F8: Fase / actividad | G8: Tarea Jira | H8: Comentarios
A9: 46303 | B9: 0.66666667 | C9: 0.77083333 | D9: 0 | E9: =ROUND(MOD(C9-B9,1)*1440,0)-D9 -> 150 | F9: Planificación | G9: SCRUM-63 | H9: Auditoría de contraste de los tokens de texto contra las superficies
A10: 46303 | B10: 0.8125 | C10: 0.95833333 | D10: 0 | E10: =ROUND(MOD(C10-B10,1)*1440,0)-D10 -> 210 | F10: Código | G10: SCRUM-63 | H10: Rampa de grises y texto secundario a WCAG AA, prueba de contraste de tokens
A11: 46304 | B11: 0.85416667 | C11: 0.03125 | D11: 15 | E11: =ROUND(MOD(C11-B11,1)*1440,0)-D11 -> 240 | F11: Pruebas | G11: SCRUM-70 | H11: Escaneo ZAP posterior al hardening y chequeos dirigidos
A12: 46305 | B12: 0.91666667 | C12: 0.0625 | D12: 30 | E12: =ROUND(MOD(C12-B12,1)*1440,0)-D12 -> 180 | F12: Pruebas | G12: SCRUM-70 | H12: Corrida de regresión de volumen e inundación
A13: 46306 | B13: 0.375 | C13: 0.53125 | D13: 15 | E13: =ROUND(MOD(C13-B13,1)*1440,0)-D13 -> 210 | F13: Código | G13: SCRUM-74 | H13: Perfil corto de k6 para CI, umbrales de cobertura y pruebas de frontend
A14: 46306 | B14: 0.53125 | C14: 0.57291667 | D14: 0 | E14: =ROUND(MOD(C14-B14,1)*1440,0)-D14 -> 60 | F14: Documentación | G14: SCRUM-70 | H14: Comparativa de resultados de volumen y hallazgos abiertos
A15: 46307 | B15: 0.75 | C15: 0.8125 | D15: 0 | E15: =ROUND(MOD(C15-B15,1)*1440,0)-D15 -> 90 | F15: Documentación | G15: SCRUM-74 | H15: Evidencia de la corrida en verde del pipeline
A16: Total | D16: =SUM(D9:D15) -> 60 | E16: =SUM(E9:E15) -> 1140
A17: Total en horas | E17: =E16/60 -> 19
A19: Nota: registro reconstruido a partir de las horas estimadas en Jira y de las fechas de los commits del sprint. Cada integrante debe revisarlo y ajustarlo a su tiempo real.

Sheet LOGT Tubac
A1: Registro de tiempo (LOGT) · Sprint 9
A3: Integrante | B3: Jonathan Tubac
A4: Carné | B4: 24484
A5: Sprint | B5: Sprint 9 (Jira: SCRUM Sprint 4), 08/10/2026 – 13/10/2026
A6: Proyecto | B6: Kontrol
A8: Fecha | B8: Inicio | C8: Fin | D8: Interrupción (min) | E8: Δ Tiempo (min) | F8: Fase / actividad | G8: Tarea Jira | H8: Comentarios
A9: 46303 | B9: 0.70833333 | C9: 0.79166667 | D9: 0 | E9: =ROUND(MOD(C9-B9,1)*1440,0)-D9 -> 120 | F9: Diseño | G9: SCRUM-67 | H9: Inventario de llamadas salientes y diseño de fetchWithTimeout
A10: 46303 | B10: 0.80208333 | C10: 0.92708333 | D10: 0 | E10: =ROUND(MOD(C10-B10,1)*1440,0)-D10 -> 180 | F10: Código | G10: SCRUM-67 | H10: fetchWithTimeout en las seis integraciones, pool y TLS de Postgres, pruebas
A11: 46305 | B11: 0.75 | C11: 0.85416667 | D11: 0 | E11: =ROUND(MOD(C11-B11,1)*1440,0)-D11 -> 150 | F11: Diseño | G11: SCRUM-65 | H11: Revisión de resultados de la Prueba 7 y propuesta de controles
A12: 46305 | B12: 0.875 | C12: 0.97916667 | D12: 0 | E12: =ROUND(MOD(C12-B12,1)*1440,0)-D12 -> 150 | F12: Código | G12: SCRUM-65 | H12: Etiqueta de pausa, peso visual de acciones, confirmación al eliminar
A13: 46306 | B13: 0.79166667 | C13: 0.875 | D13: 0 | E13: =ROUND(MOD(C13-B13,1)*1440,0)-D13 -> 120 | F13: Planificación | G13: SCRUM-72 | H13: Recolección de tareas y horas del sprint en Jira, armado de LOGT
A14: 46307 | B14: 0.58333333 | C14: 0.77083333 | D14: 30 | E14: =ROUND(MOD(C14-B14,1)*1440,0)-D14 -> 240 | F14: Documentación | G14: SCRUM-72 | H14: Cálculo de horas, monto y porcentajes del corte del Sprint 9
A15: 46307 | B15: 0.8125 | C15: 0.89583333 | D15: 0 | E15: =ROUND(MOD(C15-B15,1)*1440,0)-D15 -> 120 | F15: Documentación | G15: SCRUM-72 | H15: Interpretación de la desviación y proyección al cierre
A16: Total | D16: =SUM(D9:D15) -> 30 | E16: =SUM(E9:E15) -> 1080
A17: Total en horas | E17: =E16/60 -> 18
A19: Nota: registro reconstruido a partir de las horas estimadas en Jira y de las fechas de los commits del sprint. Cada integrante debe revisarlo y ajustarlo a su tiempo real.

Sheet LOGT Montenegro
A1: Registro de tiempo (LOGT) · Sprint 9
A3: Integrante | B3: Juan Francisco Montenegro Aguirre
A4: Carné
A5: Sprint | B5: Sprint 9 (Jira: SCRUM Sprint 4), 08/10/2026 – 13/10/2026
A6: Proyecto | B6: Kontrol
A8: Fecha | B8: Inicio | C8: Fin | D8: Interrupción (min) | E8: Δ Tiempo (min) | F8: Fase / actividad | G8: Tarea Jira | H8: Comentarios
A9: 46304 | B9: 0.75 | C9: 0.875 | D9: 0 | E9: =ROUND(MOD(C9-B9,1)*1440,0)-D9 -> 180 | F9: Planificación | G9: SCRUM-71 | H9: Revisión de los resultados no funcionales previos y de SCRUM-56
A10: 46305 | B10: 0.375 | C10: 0.5 | D10: 0 | E10: =ROUND(MOD(C10-B10,1)*1440,0)-D10 -> 180 | F10: Diseño | G10: SCRUM-71 | H10: Matriz de RNF del diseño contra resultados medidos
A11: 46305 | B11: 0.625 | C11: 0.8125 | D11: 30 | E11: =ROUND(MOD(C11-B11,1)*1440,0)-D11 -> 240 | F11: Código | G11: SCRUM-61 | H11: Carga y persistencia del idioma, selector visible en Configuración
A12: 46306 | B12: 0.39583333 | C12: 0.66666667 | D12: 30 | E12: =ROUND(MOD(C12-B12,1)*1440,0)-D12 -> 360 | F12: Código | G12: SCRUM-61 | H12: Traducción de pantallas, avisos de validación y landing en español
A13: 46307 | B13: 0.33333333 | C13: 0.54166667 | D13: 30 | E13: =ROUND(MOD(C13-B13,1)*1440,0)-D13 -> 270 | F13: Documentación | G13: SCRUM-71 | H13: Redacción de la comparativa por requisito
A14: 46307 | B14: 0.60416667 | C14: 0.70833333 | D14: 0 | E14: =ROUND(MOD(C14-B14,1)*1440,0)-D14 -> 150 | F14: Documentación | G14: SCRUM-71 | H14: Plan de refactorización derivado de la comparativa
A15: Total | D15: =SUM(D9:D14) -> 90 | E15: =SUM(E9:E14) -> 1380
A16: Total en horas | E16: =E15/60 -> 23
A18: Nota: registro reconstruido a partir de las horas estimadas en Jira y de las fechas de los commits del sprint. Cada integrante debe revisarlo y ajustarlo a su tiempo real.

Sheet LOGT Avilés
A1: Registro de tiempo (LOGT) · Sprint 9
A3: Integrante | B3: Alejandra Sarai Avilés González
A4: Carné
A5: Sprint | B5: Sprint 9 (Jira: SCRUM Sprint 4), 08/10/2026 – 13/10/2026
A6: Proyecto | B6: Kontrol
A8: Fecha | B8: Inicio | C8: Fin | D8: Interrupción (min) | E8: Δ Tiempo (min) | F8: Fase / actividad | G8: Tarea Jira | H8: Comentarios
A9: 46304 | B9: 0.66666667 | C9: 0.79166667 | D9: 0 | E9: =ROUND(MOD(C9-B9,1)*1440,0)-D9 -> 180 | F9: Diseño | G9: SCRUM-64 | H9: Propuesta de portada a partir de los hallazgos H-07 y H-13
A10: 46305 | B10: 0.41666667 | C10: 0.5625 | D10: 30 | E10: =ROUND(MOD(C10-B10,1)*1440,0)-D10 -> 180 | F10: Código | G10: SCRUM-64 | H10: Maquetación de la portada y mensaje de producto
A11: 46306 | B11: 0.70833333 | C11: 0.79166667 | D11: 0 | E11: =ROUND(MOD(C11-B11,1)*1440,0)-D11 -> 120 | F11: Revisión | G11: SCRUM-64 | H11: Ajustes y revisión responsive de la portada
A12: 46307 | B12: 0.625 | C12: 0.6875 | D12: 0 | E12: =ROUND(MOD(C12-B12,1)*1440,0)-D12 -> 90 | F12: Planificación | G12: SCRUM-73 | H12: Guion de la demo y selección de usuarios finales
A13: 46307 | B13: 0.70833333 | C13: 0.8125 | D13: 0 | E13: =ROUND(MOD(C13-B13,1)*1440,0)-D13 -> 150 | F13: Reunión | G13: SCRUM-73 | H13: Demo del incremento a usuarios finales
A14: 46307 | B14: 0.83333333 | C14: 0.875 | D14: 0 | E14: =ROUND(MOD(C14-B14,1)*1440,0)-D14 -> 60 | F14: Documentación | G14: SCRUM-73 | H14: Consolidación de comentarios y evidencia
A15: Total | D15: =SUM(D9:D14) -> 30 | E15: =SUM(E9:E14) -> 780
A16: Total en horas | E16: =E15/60 -> 13
A18: Nota: registro reconstruido a partir de las horas estimadas en Jira y de las fechas de los commits del sprint. Cada integrante debe revisarlo y ajustarlo a su tiempo real.

Sheet LOGT Figueroa
A1: Registro de tiempo (LOGT) · Sprint 9
A3: Integrante | B3: Ivana Cristina Figueroa Diemek
A4: Carné
A5: Sprint | B5: Sprint 9 (Jira: SCRUM Sprint 4), 08/10/2026 – 13/10/2026
A6: Proyecto | B6: Kontrol
A8: Fecha | B8: Inicio | C8: Fin | D8: Interrupción (min) | E8: Δ Tiempo (min) | F8: Fase / actividad | G8: Tarea Jira | H8: Comentarios
A9: 46304 | B9: 0.625 | C9: 0.70833333 | D9: 0 | E9: =ROUND(MOD(C9-B9,1)*1440,0)-D9 -> 120 | F9: Diseño | G9: SCRUM-68 | H9: Análisis del N+1 en loadOverview y diseño del endpoint agregado
A10: 46304 | B10: 0.8125 | C10: 0.95138889 | D10: 20 | E10: =ROUND(MOD(C10-B10,1)*1440,0)-D10 -> 180 | F10: Código | G10: SCRUM-68 | H10: GET /api/budgets/summary, caché de 30 s, benchmark antes/después
A11: 46306 | B11: 0.58333333 | C11: 0.77083333 | D11: 30 | E11: =ROUND(MOD(C11-B11,1)*1440,0)-D11 -> 240 | F11: Código | G11: SCRUM-62 | H11: Sección Ventas y Configuración unificada
A12: 46307 | B12: 0.625 | C12: 0.89583333 | D12: 30 | E12: =ROUND(MOD(C12-B12,1)*1440,0)-D12 -> 360 | F12: Código | G12: SCRUM-62 | H12: Router, menú, Miembros, i18n y trazabilidad en el plan de pruebas
A13: Total | D13: =SUM(D9:D12) -> 80 | E13: =SUM(E9:E12) -> 900
A14: Total en horas | E14: =E13/60 -> 15
A16: Nota: registro reconstruido a partir de las horas estimadas en Jira y de las fechas de los commits del sprint. Cada integrante debe revisarlo y ajustarlo a su tiempo real.
