Workbook

Sheet Calculo
A1: Ejecución del presupuesto y del tiempo — corte Sprint 8
A4: Línea base (SCRUM-11, SCRUM-24, SCRUM-36)
A5: Esfuerzo total estimado (H/H) | B5: 7613.67 | C5: SCRUM-11, Puntos de Casos de Uso
A6: Costo total estimado, K = 1.5 | B6: 511638.46 | C6: SCRUM-11
A7: Costo total estimado, K = 2 | B7: 682184.62 | C7: SCRUM-11
A8: Factor K bajo | B8: 1.5 | C8: Multiplica la tarifa horaria
A9: Factor K alto | B9: 2 | C9: Multiplica la tarifa horaria
A10: Peso de la actividad de implementación | B10: 0.4 | C10: Métrica dual, SCRUM-24 y SCRUM-36
A11: Horas acumuladas al cierre del Sprint 7 (H/H) | B11: 721 | C11: Reportado en SCRUM-36
A12: Monto ejecutado al cierre del Sprint 7, K = 1.5 | B12: 48701.7 | C12: Reportado en SCRUM-36
A14: Horas y monto del Sprint 8 por integrante
A15: Integrante | B15: Tarifa (Q/h) | C15: Horas del S8 (H/H) | D15: % de las horas del S8 | E15: Monto base (Q) | F15: Monto K = 1.5 (Q) | G15: Monto K = 2 (Q)
A16: Pablo Vásquez | B16: 57 | C16: =SUMIF('Tareas S8'!$C$6:$C$20,A16,'Tareas S8'!$F$6:$F$20) -> 16 | D16: =IF($C$21=0,0,C16/$C$21) -> 0.17777778 | E16: =C16*B16 -> 912 | F16: =E16*$B$8 -> 1368 | G16: =E16*$B$9 -> 1824
A17: Jonathan Tubac | B17: 51 | C17: =SUMIF('Tareas S8'!$C$6:$C$20,A17,'Tareas S8'!$F$6:$F$20) -> 22 | D17: =IF($C$21=0,0,C17/$C$21) -> 0.24444444 | E17: =C17*B17 -> 1122 | F17: =E17*$B$8 -> 1683 | G17: =E17*$B$9 -> 2244
A18: Juan Francisco Montenegro Aguirre | B18: 46 | C18: =SUMIF('Tareas S8'!$C$6:$C$20,A18,'Tareas S8'!$F$6:$F$20) -> 18 | D18: =IF($C$21=0,0,C18/$C$21) -> 0.2 | E18: =C18*B18 -> 828 | F18: =E18*$B$8 -> 1242 | G18: =E18*$B$9 -> 1656
A19: Alejandra Sarai Avilés González | B19: 36 | C19: =SUMIF('Tareas S8'!$C$6:$C$20,A19,'Tareas S8'!$F$6:$F$20) -> 19 | D19: =IF($C$21=0,0,C19/$C$21) -> 0.21111111 | E19: =C19*B19 -> 684 | F19: =E19*$B$8 -> 1026 | G19: =E19*$B$9 -> 1368
A20: Ivana Cristina Figueroa Diemek | B20: 34 | C20: =SUMIF('Tareas S8'!$C$6:$C$20,A20,'Tareas S8'!$F$6:$F$20) -> 15 | D20: =IF($C$21=0,0,C20/$C$21) -> 0.16666667 | E20: =C20*B20 -> 510 | F20: =E20*$B$8 -> 765 | G20: =E20*$B$9 -> 1020
A21: Total | B21: =IF(C21=0,0,E21/C21) -> 45.066667 | C21: =SUM(C16:C20) -> 90 | D21: =SUM(D16:D20) -> 1 | E21: =SUM(E16:E20) -> 4056 | F21: =SUM(F16:F20) -> 6084 | G21: =SUM(G16:G20) -> 8112
A25: Resultados y variación respecto del corte del Sprint 7
A26: Indicador | B26: Corte Sprint 7 | C26: Corte Sprint 8 | D26: Variación
A27: Horas acumuladas (H/H) | B27: =B11 -> 721 | C27: =B11+C21 -> 811 | D27: =C27-B27 -> 90
A28: % del esfuerzo total (ciclo completo) | B28: =B27/$B$5 -> 0.094698089 | C28: =C27/$B$5 -> 0.10651893 | D28: =(C28-B28)*100 -> 1.1820843
A29: % de la actividad de implementación (40 %) | B29: =B27/($B$5*$B$10) -> 0.23674522 | C29: =C27/($B$5*$B$10) -> 0.26629733 | D29: =(C29-B29)*100 -> 2.9552108
A30: Monto ejecutado, K = 1.5 | B30: =B12 -> 48701.7 | C30: =B12+F21 -> 54785.7 | D30: =C30-B30 -> 6084
A31: % del costo total, K = 1.5 | B31: =B30/$B$6 -> 0.095187723 | C31: =C30/$B$6 -> 0.10707893 | D31: =(C31-B31)*100 -> 1.1891209
A32: Monto ejecutado, K = 2 | B32: =B12/$B$8*$B$9 -> 64935.6 | C32: =B32+G21 -> 73047.6 | D32: =C32-B32 -> 8112
A33: % del costo total, K = 2 | B33: =B32/$B$7 -> 0.095187722 | C33: =C32/$B$7 -> 0.10707893 | D33: =(C33-B33)*100 -> 1.1891209
A34: % del costo de implementación, K = 1.5 | B34: =B30/($B$6*$B$10) -> 0.23796931 | C34: =C30/($B$6*$B$10) -> 0.26769733 | D34: =(C34-B34)*100 -> 2.9728023

Sheet Tareas S8
A1: Tareas del Sprint 8 en Jira (SCRUM Sprint 3) y horas estimadas
A3: Razón horas / SP (tareas con horas estimadas) | D3: =SUM(E6:E20)/SUMIFS(D6:D20,E6:E20,"<>") -> 1.5769231
A5: Clave | B5: Tarea | C5: Responsable | D5: SP | E5: Horas estimadas en Jira | F5: Horas usadas | G5: Origen de las horas
A6: SCRUM-37 | B6: DT-06 · Denominador de cobertura y trinquete de CI | C6: Pablo Vásquez | D6: 5 | F6: =IF(E6="",ROUND(D6*$D$3,0),E6) -> 8 | G6: =IF(E6="","Derivada de SP","Estimación de Jira") -> Derivada de SP
A7: SCRUM-38 | B7: DT-01 · Middleware central de errores y asyncHandler | C7: Jonathan Tubac | D7: 3 | F7: =IF(E7="",ROUND(D7*$D$3,0),E7) -> 5 | G7: =IF(E7="","Derivada de SP","Estimación de Jira") -> Derivada de SP
A8: SCRUM-39 | B8: DT-02 · Precios, descuento e IVA en el servidor (POS) | C8: Juan Francisco Montenegro Aguirre | D8: 5 | F8: =IF(E8="",ROUND(D8*$D$3,0),E8) -> 8 | G8: =IF(E8="","Derivada de SP","Estimación de Jira") -> Derivada de SP
A9: SCRUM-40 | B9: DT-03 · Unicidad de código de barras y resolución del escaneo | C9: Juan Francisco Montenegro Aguirre | D9: 3 | F9: =IF(E9="",ROUND(D9*$D$3,0),E9) -> 5 | G9: =IF(E9="","Derivada de SP","Estimación de Jira") -> Derivada de SP
A10: SCRUM-41 | B10: DT-04 · Parámetro de los endpoints producto-proveedor | C10: Ivana Cristina Figueroa Diemek | D10: 1 | F10: =IF(E10="",ROUND(D10*$D$3,0),E10) -> 2 | G10: =IF(E10="","Derivada de SP","Estimación de Jira") -> Derivada de SP
A11: SCRUM-42 | B11: DT-05 · Modelo de autorización en inventario y proveedores | C11: Alejandra Sarai Avilés González | D11: 5 | F11: =IF(E11="",ROUND(D11*$D$3,0),E11) -> 8 | G11: =IF(E11="","Derivada de SP","Estimación de Jira") -> Derivada de SP
A12: SCRUM-43 | B12: DT-12 · SSRF del probador de integraciones | C12: Ivana Cristina Figueroa Diemek | D12: 3 | F12: =IF(E12="",ROUND(D12*$D$3,0),E12) -> 5 | G12: =IF(E12="","Derivada de SP","Estimación de Jira") -> Derivada de SP
A13: SCRUM-44 | B13: DT-13 · Límite de intentos en autenticación y endpoints costosos | C13: Jonathan Tubac | D13: 3 | F13: =IF(E13="",ROUND(D13*$D$3,0),E13) -> 5 | G13: =IF(E13="","Derivada de SP","Estimación de Jira") -> Derivada de SP
A14: SCRUM-45 | B14: DT-14 · Cabeceras de seguridad HTTP | C14: Alejandra Sarai Avilés González | D14: 2 | F14: =IF(E14="",ROUND(D14*$D$3,0),E14) -> 3 | G14: =IF(E14="","Derivada de SP","Estimación de Jira") -> Derivada de SP
A15: SCRUM-52 | B15: Pruebas de seguridad automatizadas con OWASP ZAP | C15: Pablo Vásquez | D15: 5 | E15: 8 | F15: =IF(E15="",ROUND(D15*$D$3,0),E15) -> 8 | G15: =IF(E15="","Derivada de SP","Estimación de Jira") -> Estimación de Jira
A16: SCRUM-53 | B16: Pruebas de volumen e inundación sobre la base de datos | C16: Jonathan Tubac | D16: 5 | E16: 8 | F16: =IF(E16="",ROUND(D16*$D$3,0),E16) -> 8 | G16: =IF(E16="","Derivada de SP","Estimación de Jira") -> Estimación de Jira
A17: SCRUM-54 | B17: Sesiones de usabilidad sobre las pantallas de la Fase 2 | C17: Alejandra Sarai Avilés González | D17: 5 | E17: 8 | F17: =IF(E17="",ROUND(D17*$D$3,0),E17) -> 8 | G17: =IF(E17="","Derivada de SP","Estimación de Jira") -> Estimación de Jira
A18: SCRUM-55 | B18: Análisis de hallazgos de usabilidad y backlog de mejoras | C18: Juan Francisco Montenegro Aguirre | D18: 3 | E18: 5 | F18: =IF(E18="",ROUND(D18*$D$3,0),E18) -> 5 | G18: =IF(E18="","Derivada de SP","Estimación de Jira") -> Estimación de Jira
A19: SCRUM-56 | B19: Análisis de requisitos no funcionales y plan de refactorización | C19: Ivana Cristina Figueroa Diemek | D19: 5 | E19: 8 | F19: =IF(E19="",ROUND(D19*$D$3,0),E19) -> 8 | G19: =IF(E19="","Derivada de SP","Estimación de Jira") -> Estimación de Jira
A20: SCRUM-57 | B20: Ejecución del presupuesto y del tiempo del proyecto | C20: Jonathan Tubac | D20: 3 | E20: 4 | F20: =IF(E20="",ROUND(D20*$D$3,0),E20) -> 4 | G20: =IF(E20="","Derivada de SP","Estimación de Jira") -> Estimación de Jira
A21: Total | D21: =SUM(D6:D20) -> 56 | E21: =SUM(E6:E20) -> 41 | F21: =SUM(F6:F20) -> 90

Sheet Texto
A1: Texto para el informe
A3: ="En el Sprint 8 se registran "&TEXT(Calculo!C21,"#,##0")&" H/H,. Con ello el equipo acumula "&TEXT(Calculo!C27,"#,##0")&" H/H, equivalentes al "&TEXT(Calculo!C28,"0.00%")&" del esfuerzo total estimado de "&TEXT(Calculo!B5,"#,##0.00")&" H/H, un avance de "&TEXT(Calculo!D28,"0.00")&" puntos porcentuales respecto del corte del Sprint 7 ("&TEXT(Calculo!B28,"0.00%")&")." -> En el Sprint 8 se registran 90 H/H,. Con ello el equipo acumula 811 H/H, equivalentes al 10.65% del esfuerzo total estimado de 7,613.67 H/H, un avance de 1.18 puntos porcentuales respecto del corte del Sprint 7 (9.47%).
A5: ="Con la tarifa individual de cada integrante, el Sprint 8 suma Q "&TEXT(Calculo!F21,"#,##0.00")&" con K = 1.5, y el monto ejecutado acumulado asciende a Q "&TEXT(Calculo!C30,"#,##0.00")&", el "&TEXT(Calculo!C31,"0.00%")&" del costo total estimado (Q "&TEXT(Calculo!B6,"#,##0.00")&"). Con K = 2 son Q "&TEXT(Calculo!C32,"#,##0.00")&" sobre Q "&TEXT(Calculo!B7,"#,##0.00")&", la misma proporción. Frente al Sprint 7, el porcentaje de costo avanza "&TEXT(Calculo!D31,"0.00")&" puntos porcentuales." -> Con la tarifa individual de cada integrante, el Sprint 8 suma Q 6,084.00 con K = 1.5, y el monto ejecutado acumulado asciende a Q 54,785.70, el 10.71% del costo total estimado (Q 511,638.46). Con K = 2 son Q 73,047.60 sobre Q 682,184.62, la misma proporción. Frente al Sprint 7, el porcentaje de costo avanza 1.19 puntos porcentuales.
A7: ="Métrica dual: frente al esfuerzo de ciclo completo del PCU se ha consumido el "&TEXT(Calculo!C28,"0.00%")&"; frente a la actividad de implementación (40 % del esfuerzo, "&TEXT(Calculo!B5*Calculo!B10,"#,##0.00")&" H/H) el consumo es del "&TEXT(Calculo!C29,"0.00%")&", y en costo del "&TEXT(Calculo!C34,"0.00%")&"." -> Métrica dual: frente al esfuerzo de ciclo completo del PCU se ha consumido el 10.65%; frente a la actividad de implementación (40 % del esfuerzo, 3,045.47 H/H) el consumo es del 26.63%, y en costo del 26.77%.
A9: =_xlfn._LONGTEXT("Interpretación: el método de Karner está calibrado para el ciclo de vida profesional completo (análisis, diseño, implementación, pruebas, despliegue y gestión), por lo que opera como cota superior. Un porcentaje bajo frente al PCU, con un backlog funciona","l prácticamente completo, no indica un error de cálculo: refleja que la estimación incluye actividades que un proyecto académico no ejecuta con esa intensidad. El porcentaje frente a la implementación es la lectura más cercana al trabajo realizado.") -> Interpretación: el método de Karner está calibrado para el ciclo de vida profesional completo (análisis, diseño, implementación, pruebas, despliegue y gestión), por lo que opera como cota superior. Un porcentaje bajo frente al PCU, con un backlog funcional prácticamente completo, no indica un error de cálculo: refleja que la estimación incluye actividades que un proyecto académico no ejecuta con esa intensidad. El porcentaje frente a la implementación es la lectura más cercana al trabajo realizado.
